[
    {
        "type": "message",
        "user": "U0J3LL9PB",
        "text": "melonse",
        "ts": "1453828360.000030"
    },
    {
        "type": "message",
        "user": "U0J1XCZAP",
        "text": "Nimiety (noun, ni-mahy-i-tee) - excess; overabundance.",
        "ts": "1453828396.000031"
    },
    {
        "type": "message",
        "user": "U0J1YGMUK",
        "text": "Pangolin",
        "ts": "1453830756.000032"
    },
    {
        "type": "message",
        "user": "U0J235A57",
        "text": "Aardvark",
        "ts": "1453832157.000033"
    },
    {
        "type": "message",
        "user": "U0J242FDE",
        "text": "I didn't make it",
        "ts": "1453832252.000034"
    },
    {
        "type": "message",
        "user": "U0J1X7VT5",
        "text": "hi",
        "ts": "1453834836.000035"
    },
    {
        "type": "message",
        "user": "U0J1XP6NA",
        "text": "The",
        "ts": "1453834905.000036"
    },
    {
        "type": "message",
        "user": "U0J2U3PJT",
        "text": "Cock a doodle - doo the cow says moo",
        "ts": "1453835461.000037"
    },
    {
        "type": "message",
        "user": "U0J1V4ABW",
        "text": "\/\\~\/\\",
        "ts": "1453837309.000038"
    },
    {
        "type": "message",
        "user": "U0J6T6ARG",
        "text": "ALIVE",
        "ts": "1453846393.000039"
    },
    {
        "type": "message",
        "user": "U0J235A57",
        "text": "10\/12",
        "ts": "1453870413.000040"
    },
    {
        "type": "message",
        "user": "U0J235A57",
        "text": "~~~~~~~~~~~~~~~~~~~~BREAK LINE ~~~~~~~~~~~~~~~~~~~~~~~~~~~~",
        "ts": "1453872126.000041"
    }
]